[{"duration":"1986","startMillisecond":"34","lineWidth":"1","stroke":[{"x":"554.375","y":"671.375","pressure":"0","deltaTime":"0"},{"x":"554.25","y":"671.375","pressure":"92","deltaTime":"13"},{"x":"554.375","y":"671.5","pressure":"112","deltaTime":"27"},{"x":"555.75","y":"673.5","pressure":"118","deltaTime":"53"},{"x":"559.5","y":"682.75","pressure":"120","deltaTime":"93"},{"x":"564.875","y":"689.875","pressure":"122","deltaTime":"67"},{"x":"566","y":"690.625","pressure":"122","deltaTime":"67"},{"x":"564.875","y":"689.625","pressure":"122","deltaTime":"40"},{"x":"564","y":"688.75","pressure":"120","deltaTime":"13"},{"x":"563","y":"687.25","pressure":"114","deltaTime":"13"},{"x":"562.25","y":"685.25","pressure":"0","deltaTime":"14"},{"x":"562.375","y":"676.125","pressure":"118","deltaTime":"0"},{"x":"571.625","y":"672.75","pressure":"120","deltaTime":"53"},{"x":"575.375","y":"671.875","pressure":"120","deltaTime":"13"},{"x":"579.125","y":"671.25","pressure":"120","deltaTime":"14"},{"x":"589.25","y":"671.125","pressure":"122","deltaTime":"146"},{"x":"589.375","y":"671.75","pressure":"122","deltaTime":"160"},{"x":"587.375","y":"676.75","pressure":"122","deltaTime":"80"},{"x":"581.25","y":"688.25","pressure":"122","deltaTime":"67"},{"x":"578.25","y":"690.625","pressure":"122","deltaTime":"53"},{"x":"576.375","y":"690.625","pressure":"124","deltaTime":"80"},{"x":"576.25","y":"690.375","pressure":"124","deltaTime":"120"},{"x":"575","y":"688.625","pressure":"106","deltaTime":"40"},{"x":"574.625","y":"652.5","pressure":"116","deltaTime":"0"},{"x":"570.25","y":"689.5","pressure":"122","deltaTime":"320"},{"x":"568.75","y":"687.75","pressure":"122","deltaTime":"66"},{"x":"564.625","y":"683","pressure":"86","deltaTime":"94"},{"x":"571.125","y":"679.25","pressure":"122","deltaTime":"280"},{"x":"573.375","y":"678.5","pressure":"122","deltaTime":"13"},{"x":"577.5","y":"677.75","pressure":"122","deltaTime":"27"},{"x":"579.625","y":"678.25","pressure":"122","deltaTime":"66"},{"x":"576.375","y":"679.75","pressure":"122","deltaTime":"160"},{"x":"568.25","y":"688.125","pressure":"122","deltaTime":"94"},{"x":"564.5","y":"691.375","pressure":"122","deltaTime":"173"},{"x":"571.25","y":"688.875","pressure":"122","deltaTime":"107"},{"x":"577","y":"688.875","pressure":"122","deltaTime":"40"},{"x":"578.125","y":"689.375","pressure":"122","deltaTime":"40"},{"x":"576.75","y":"689","pressure":"122","deltaTime":"53"},{"x":"575.25","y":"688.625","pressure":"120","deltaTime":"13"},{"x":"572.625","y":"688.25","pressure":"0","deltaTime":"14"},{"x":"548.75","y":"686.5","pressure":"118","deltaTime":"0"},{"x":"550","y":"689.875","pressure":"120","deltaTime":"26"},{"x":"552.125","y":"693.25","pressure":"122","deltaTime":"40"},{"x":"557","y":"698.125","pressure":"122","deltaTime":"134"},{"x":"556.5","y":"697.625","pressure":"122","deltaTime":"40"},{"x":"552.75","y":"696.75","pressure":"122","deltaTime":"53"},{"x":"544.125","y":"697.5","pressure":"122","deltaTime":"120"},{"x":"542.125","y":"698.25","pressure":"122","deltaTime":"187"},{"x":"546.875","y":"697.5","pressure":"122","deltaTime":"160"},{"x":"554.625","y":"697.125","pressure":"122","deltaTime":"173"},{"x":"566","y":"697.5","pressure":"122","deltaTime":"240"},{"x":"577.375","y":"698.75","pressure":"122","deltaTime":"133"},{"x":"591.125","y":"702.75","pressure":"124","deltaTime":"280"},{"x":"591.875","y":"702.625","pressure":"124","deltaTime":"94"},{"x":"595.75","y":"697.5","pressure":"56","deltaTime":"306"}]},{"duration":"1986","startMillisecond":"34","lineWidth":"1","stroke":[{"x":"554.375","y":"671.375","pressure":"0","deltaTime":"0"},{"x":"554.25","y":"671.375","pressure":"92","deltaTime":"13"},{"x":"554.375","y":"671.5","pressure":"112","deltaTime":"27"},{"x":"555.75","y":"673.5","pressure":"118","deltaTime":"53"},{"x":"559.5","y":"682.75","pressure":"120","deltaTime":"93"},{"x":"564.875","y":"689.875","pressure":"122","deltaTime":"67"},{"x":"566","y":"690.625","pressure":"122","deltaTime":"67"},{"x":"564.875","y":"689.625","pressure":"122","deltaTime":"40"},{"x":"564","y":"688.75","pressure":"120","deltaTime":"13"},{"x":"563","y":"687.25","pressure":"114","deltaTime":"13"},{"x":"562.25","y":"685.25","pressure":"0","deltaTime":"14"},{"x":"562.375","y":"676.125","pressure":"118","deltaTime":"0"},{"x":"571.625","y":"672.75","pressure":"120","deltaTime":"53"},{"x":"575.375","y":"671.875","pressure":"120","deltaTime":"13"},{"x":"579.125","y":"671.25","pressure":"120","deltaTime":"14"},{"x":"589.25","y":"671.125","pressure":"122","deltaTime":"146"},{"x":"589.375","y":"671.75","pressure":"122","deltaTime":"160"},{"x":"587.375","y":"676.75","pressure":"122","deltaTime":"80"},{"x":"581.25","y":"688.25","pressure":"122","deltaTime":"67"},{"x":"578.25","y":"690.625","pressure":"122","deltaTime":"53"},{"x":"576.375","y":"690.625","pressure":"124","deltaTime":"80"},{"x":"576.25","y":"690.375","pressure":"124","deltaTime":"120"},{"x":"575","y":"688.625","pressure":"106","deltaTime":"40"},{"x":"574.625","y":"652.5","pressure":"116","deltaTime":"0"},{"x":"570.25","y":"689.5","pressure":"122","deltaTime":"320"},{"x":"568.75","y":"687.75","pressure":"122","deltaTime":"66"},{"x":"564.625","y":"683","pressure":"86","deltaTime":"94"},{"x":"571.125","y":"679.25","pressure":"122","deltaTime":"280"},{"x":"573.375","y":"678.5","pressure":"122","deltaTime":"13"},{"x":"577.5","y":"677.75","pressure":"122","deltaTime":"27"},{"x":"579.625","y":"678.25","pressure":"122","deltaTime":"66"},{"x":"576.375","y":"679.75","pressure":"122","deltaTime":"160"},{"x":"568.25","y":"688.125","pressure":"122","deltaTime":"94"},{"x":"564.5","y":"691.375","pressure":"122","deltaTime":"173"},{"x":"571.25","y":"688.875","pressure":"122","deltaTime":"107"},{"x":"577","y":"688.875","pressure":"122","deltaTime":"40"},{"x":"578.125","y":"689.375","pressure":"122","deltaTime":"40"},{"x":"576.75","y":"689","pressure":"122","deltaTime":"53"},{"x":"575.25","y":"688.625","pressure":"120","deltaTime":"13"},{"x":"572.625","y":"688.25","pressure":"0","deltaTime":"14"},{"x":"548.75","y":"686.5","pressure":"118","deltaTime":"0"},{"x":"550","y":"689.875","pressure":"120","deltaTime":"26"},{"x":"552.125","y":"693.25","pressure":"122","deltaTime":"40"},{"x":"557","y":"698.125","pressure":"122","deltaTime":"134"},{"x":"556.5","y":"697.625","pressure":"122","deltaTime":"40"},{"x":"552.75","y":"696.75","pressure":"122","deltaTime":"53"},{"x":"544.125","y":"697.5","pressure":"122","deltaTime":"120"},{"x":"542.125","y":"698.25","pressure":"122","deltaTime":"187"},{"x":"546.875","y":"697.5","pressure":"122","deltaTime":"160"},{"x":"554.625","y":"697.125","pressure":"122","deltaTime":"173"},{"x":"566","y":"697.5","pressure":"122","deltaTime":"240"},{"x":"577.375","y":"698.75","pressure":"122","deltaTime":"133"},{"x":"591.125","y":"702.75","pressure":"124","deltaTime":"280"},{"x":"591.875","y":"702.625","pressure":"124","deltaTime":"94"},{"x":"595.75","y":"697.5","pressure":"56","deltaTime":"306"}]},{"duration":"1986","startMillisecond":"34","lineWidth":"1","stroke":[{"x":"554.375","y":"671.375","pressure":"0","deltaTime":"0"},{"x":"554.25","y":"671.375","pressure":"92","deltaTime":"13"},{"x":"554.375","y":"671.5","pressure":"112","deltaTime":"27"},{"x":"555.75","y":"673.5","pressure":"118","deltaTime":"53"},{"x":"559.5","y":"682.75","pressure":"120","deltaTime":"93"},{"x":"564.875","y":"689.875","pressure":"122","deltaTime":"67"},{"x":"566","y":"690.625","pressure":"122","deltaTime":"67"},{"x":"564.875","y":"689.625","pressure":"122","deltaTime":"40"},{"x":"564","y":"688.75","pressure":"120","deltaTime":"13"},{"x":"563","y":"687.25","pressure":"114","deltaTime":"13"},{"x":"562.25","y":"685.25","pressure":"0","deltaTime":"14"},{"x":"562.375","y":"676.125","pressure":"118","deltaTime":"0"},{"x":"571.625","y":"672.75","pressure":"120","deltaTime":"53"},{"x":"575.375","y":"671.875","pressure":"120","deltaTime":"13"},{"x":"579.125","y":"671.25","pressure":"120","deltaTime":"14"},{"x":"589.25","y":"671.125","pressure":"122","deltaTime":"146"},{"x":"589.375","y":"671.75","pressure":"122","deltaTime":"160"},{"x":"587.375","y":"676.75","pressure":"122","deltaTime":"80"},{"x":"581.25","y":"688.25","pressure":"122","deltaTime":"67"},{"x":"578.25","y":"690.625","pressure":"122","deltaTime":"53"},{"x":"576.375","y":"690.625","pressure":"124","deltaTime":"80"},{"x":"576.25","y":"690.375","pressure":"124","deltaTime":"120"},{"x":"575","y":"688.625","pressure":"106","deltaTime":"40"},{"x":"574.625","y":"652.5","pressure":"116","deltaTime":"0"},{"x":"570.25","y":"689.5","pressure":"122","deltaTime":"320"},{"x":"568.75","y":"687.75","pressure":"122","deltaTime":"66"},{"x":"564.625","y":"683","pressure":"86","deltaTime":"94"},{"x":"571.125","y":"679.25","pressure":"122","deltaTime":"280"},{"x":"573.375","y":"678.5","pressure":"122","deltaTime":"13"},{"x":"577.5","y":"677.75","pressure":"122","deltaTime":"27"},{"x":"579.625","y":"678.25","pressure":"122","deltaTime":"66"},{"x":"576.375","y":"679.75","pressure":"122","deltaTime":"160"},{"x":"568.25","y":"688.125","pressure":"122","deltaTime":"94"},{"x":"564.5","y":"691.375","pressure":"122","deltaTime":"173"},{"x":"571.25","y":"688.875","pressure":"122","deltaTime":"107"},{"x":"577","y":"688.875","pressure":"122","deltaTime":"40"},{"x":"578.125","y":"689.375","pressure":"122","deltaTime":"40"},{"x":"576.75","y":"689","pressure":"122","deltaTime":"53"},{"x":"575.25","y":"688.625","pressure":"120","deltaTime":"13"},{"x":"572.625","y":"688.25","pressure":"0","deltaTime":"14"},{"x":"548.75","y":"686.5","pressure":"118","deltaTime":"0"},{"x":"550","y":"689.875","pressure":"120","deltaTime":"26"},{"x":"552.125","y":"693.25","pressure":"122","deltaTime":"40"},{"x":"557","y":"698.125","pressure":"122","deltaTime":"134"},{"x":"556.5","y":"697.625","pressure":"122","deltaTime":"40"},{"x":"552.75","y":"696.75","pressure":"122","deltaTime":"53"},{"x":"544.125","y":"697.5","pressure":"122","deltaTime":"120"},{"x":"542.125","y":"698.25","pressure":"122","deltaTime":"187"},{"x":"546.875","y":"697.5","pressure":"122","deltaTime":"160"},{"x":"554.625","y":"697.125","pressure":"122","deltaTime":"173"},{"x":"566","y":"697.5","pressure":"122","deltaTime":"240"},{"x":"577.375","y":"698.75","pressure":"122","deltaTime":"133"},{"x":"591.125","y":"702.75","pressure":"124","deltaTime":"280"},{"x":"591.875","y":"702.625","pressure":"124","deltaTime":"94"},{"x":"595.75","y":"697.5","pressure":"56","deltaTime":"306"}]},{"duration":"1986","startMillisecond":"34","lineWidth":"1","stroke":[{"x":"554.375","y":"671.375","pressure":"0","deltaTime":"0"},{"x":"554.25","y":"671.375","pressure":"92","deltaTime":"13"},{"x":"554.375","y":"671.5","pressure":"112","deltaTime":"27"},{"x":"555.75","y":"673.5","pressure":"118","deltaTime":"53"},{"x":"559.5","y":"682.75","pressure":"120","deltaTime":"93"},{"x":"564.875","y":"689.875","pressure":"122","deltaTime":"67"},{"x":"566","y":"690.625","pressure":"122","deltaTime":"67"},{"x":"564.875","y":"689.625","pressure":"122","deltaTime":"40"},{"x":"564","y":"688.75","pressure":"120","deltaTime":"13"},{"x":"563","y":"687.25","pressure":"114","deltaTime":"13"},{"x":"562.25","y":"685.25","pressure":"0","deltaTime":"14"},{"x":"562.375","y":"676.125","pressure":"118","deltaTime":"0"},{"x":"571.625","y":"672.75","pressure":"120","deltaTime":"53"},{"x":"575.375","y":"671.875","pressure":"120","deltaTime":"13"},{"x":"579.125","y":"671.25","pressure":"120","deltaTime":"14"},{"x":"589.25","y":"671.125","pressure":"122","deltaTime":"146"},{"x":"589.375","y":"671.75","pressure":"122","deltaTime":"160"},{"x":"587.375","y":"676.75","pressure":"122","deltaTime":"80"},{"x":"581.25","y":"688.25","pressure":"122","deltaTime":"67"},{"x":"578.25","y":"690.625","pressure":"122","deltaTime":"53"},{"x":"576.375","y":"690.625","pressure":"124","deltaTime":"80"},{"x":"576.25","y":"690.375","pressure":"124","deltaTime":"120"},{"x":"575","y":"688.625","pressure":"106","deltaTime":"40"},{"x":"574.625","y":"652.5","pressure":"116","deltaTime":"0"},{"x":"570.25","y":"689.5","pressure":"122","deltaTime":"320"},{"x":"568.75","y":"687.75","pressure":"122","deltaTime":"66"},{"x":"564.625","y":"683","pressure":"86","deltaTime":"94"},{"x":"571.125","y":"679.25","pressure":"122","deltaTime":"280"},{"x":"573.375","y":"678.5","pressure":"122","deltaTime":"13"},{"x":"577.5","y":"677.75","pressure":"122","deltaTime":"27"},{"x":"579.625","y":"678.25","pressure":"122","deltaTime":"66"},{"x":"576.375","y":"679.75","pressure":"122","deltaTime":"160"},{"x":"568.25","y":"688.125","pressure":"122","deltaTime":"94"},{"x":"564.5","y":"691.375","pressure":"122","deltaTime":"173"},{"x":"571.25","y":"688.875","pressure":"122","deltaTime":"107"},{"x":"577","y":"688.875","pressure":"122","deltaTime":"40"},{"x":"578.125","y":"689.375","pressure":"122","deltaTime":"40"},{"x":"576.75","y":"689","pressure":"122","deltaTime":"53"},{"x":"575.25","y":"688.625","pressure":"120","deltaTime":"13"},{"x":"572.625","y":"688.25","pressure":"0","deltaTime":"14"},{"x":"548.75","y":"686.5","pressure":"118","deltaTime":"0"},{"x":"550","y":"689.875","pressure":"120","deltaTime":"26"},{"x":"552.125","y":"693.25","pressure":"122","deltaTime":"40"},{"x":"557","y":"698.125","pressure":"122","deltaTime":"134"},{"x":"556.5","y":"697.625","pressure":"122","deltaTime":"40"},{"x":"552.75","y":"696.75","pressure":"122","deltaTime":"53"},{"x":"544.125","y":"697.5","pressure":"122","deltaTime":"120"},{"x":"542.125","y":"698.25","pressure":"122","deltaTime":"187"},{"x":"546.875","y":"697.5","pressure":"122","deltaTime":"160"},{"x":"554.625","y":"697.125","pressure":"122","deltaTime":"173"},{"x":"566","y":"697.5","pressure":"122","deltaTime":"240"},{"x":"577.375","y":"698.75","pressure":"122","deltaTime":"133"},{"x":"591.125","y":"702.75","pressure":"124","deltaTime":"280"},{"x":"591.875","y":"702.625","pressure":"124","deltaTime":"94"},{"x":"595.75","y":"697.5","pressure":"56","deltaTime":"306"}]}]